befordata/__init__.py
befordata/_epochs.py
befordata/_misc.py
befordata/_record.py
befordata/_tools.py
befordata/arrow.py
befordata/csv.py
befordata/filtering.py
befordata/xdf.py
befordata/plot/__init__.py
befordata/plot/interactive_plot.py
befordata-0.4.4.dist-info/licenses/LICENSE
befordata-0.4.4.dist-info/WHEEL
befordata-0.4.4.dist-info/METADATA
befordata-0.4.4.dist-info/RECORD
