Metadata-Version: 2.4
Name: befordata
Version: 0.4.4
Summary: BeForData: Python data structures for handling behavioural force data.
Author-email: Oliver Lindemann <lindemann@essb.eur.nl>
Requires-Python: >=3.10
Classifier: License :: OSI Approved :: MIT License
License-File: LICENSE
Requires-Dist: numpy>=2.2.6
Requires-Dist: pandas>=2.3.1
Requires-Dist: scipy>=1.15.3
Requires-Dist: pyarrow>=21.0.0 ; extra == "arrow"
Requires-Dist: sphinx>=8.1 ; extra == "docs"
Requires-Dist: pydata-sphinx-theme>=0.16.0 ; extra == "docs"
Requires-Dist: sphinx_autodoc_typehints>=2.5.0 ; extra == "docs"
Requires-Dist: numpydoc>=1.7 ; extra == "docs"
Requires-Dist: myst_parser>=4.0 ; extra == "docs"
Requires-Dist: matplotlib>=3.10.5 ; extra == "plot"
Project-URL: Home, https://github.com/lindemann09/befordata
Provides-Extra: arrow
Provides-Extra: docs
Provides-Extra: plot
